nonebot_plugin_bf6_stats-0.1.2.dist-info/METADATA
nonebot_plugin_bf6_stats-0.1.2.dist-info/WHEEL
nonebot_plugin_bf6_stats-0.1.2.dist-info/entry_points.txt
nonebot_plugin_bf6_stats-0.1.2.dist-info/licenses/LICENSE
nonebot_plugin_bf6_stats/__init__.py
nonebot_plugin_bf6_stats/data_source.py
nonebot_plugin_bf6_stats/models.py
nonebot_plugin_bf6_stats-0.1.2.dist-info/RECORD
