Metadata-Version: 2.1
Name: nonebot-plugin-bf6-stats
Version: 0.1.2
Summary: 基于 NoneBot2 的战地6 战绩查询插件
Keywords: nonebot,nonebot2,battlefield,bf2042,plugin
Author-Email: Xfjie314 <2075553664@qq.com>
License: MIT License
Classifier: Programming Language :: Python :: 3
Classifier: License :: OSI Approved :: MIT License
Classifier: Operating System :: OS Independent
Classifier: Framework :: Pydantic
Classifier: Framework :: Pydantic :: 2
Project-URL: Homepage, https://github.com/Xfjie314/nonebot-plugin-bf6-stats
Project-URL: Repository, https://github.com/Xfjie314/nonebot-plugin-bf6-stats
Project-URL: Issues, https://github.com/Xfjie314/nonebot-plugin-bf6-stats/issues
Requires-Python: >=3.9
Requires-Dist: nonebot2>=2.3.0
Requires-Dist: httpx<1.0.0,>=0.20.0
